goli/__init__.py
goli/__main__.py
goli/cookiecutters.py
goli/options.py
goli/py.typed
goli-0.1.1.dist-info/entry_points.txt
goli-0.1.1.dist-info/LICENSE
goli-0.1.1.dist-info/WHEEL
goli-0.1.1.dist-info/METADATA
goli-0.1.1.dist-info/RECORD
