Metadata-Version: 2.1
Name: goli
Version: 0.1.1
Summary: A sophisticated boilerplate generator based on best practices and modern useful templates
Home-page: https://github.com/nidhaloff/goli
License: MIT
Keywords: goli,boilerplate,boilerplate-generator,code-generator,cookiecutter
Author: nidhaloff
Author-email: nidhalbacc@gmail.com
Requires-Python: >=3.7,<4.0
Classifier: Development Status :: 4 - Beta
Classifier: Intended Audience :: Developers
Classifier: License :: OSI Approved :: MIT License
Classifier: Operating System :: OS Independent
Classifier: Programming Language :: Python :: 3
Classifier: Programming Language :: Python :: 3.7
Classifier: Programming Language :: Python :: 3.8
Classifier: Programming Language :: Python :: 3.9
Classifier: Topic :: Software Development :: Libraries :: Python Modules
Requires-Dist: cookiecutter (>=1.7.3,<2.0.0)
Project-URL: Repository, https://github.com/nidhaloff/goli
